{"is_source_file": true, "format": "HTML", "description": "The main HTML template for the KAVIA AI application, defining the structure of the webpage with metadata, links to resources, and a root div for the main application components.", "external_files": ["%PUBLIC_URL%/favicon.ico", "%PUBLIC_URL%/logo192.png", "%PUBLIC_URL%/manifest.json"], "external_methods": [], "published": [], "classes": [], "methods": [], "calls": [], "search-terms": ["KAVIA", "AI Application", "HTML Template", "Frontend Structure"], "state": 2, "file_id": 10, "knowledge_revision": 18, "git_revision": "68d7c20cf99ef9c3c3c5d42f71b7798da5defff4", "hash": "d2b40d02d5f7873d8a6713bad837edd4", "format-version": 4, "code-base-name": "tic_tac_toe_frontend", "filename": "tic_tac_toe_frontend/public/index.html", "revision_history": [{"18": "68d7c20cf99ef9c3c3c5d42f71b7798da5defff4"}]}